adopt_net0/__init__.py
adopt_net0/case_studies/__init__.py
adopt_net0/case_studies/data/data_household.xlsx
adopt_net0/case_studies/data/data_network_city.xlsx
adopt_net0/case_studies/data/data_network_rural.xlsx
adopt_net0/case_studies/load_case_study_data.py
adopt_net0/components/__init__.py
adopt_net0/components/component.py
adopt_net0/components/networks/__init__.py
adopt_net0/components/networks/genericNetworks/__init__.py
adopt_net0/components/networks/genericNetworks/electricity.py
adopt_net0/components/networks/genericNetworks/fluid.py
adopt_net0/components/networks/genericNetworks/simple.py
adopt_net0/components/networks/network.py
adopt_net0/components/technologies/__init__.py
adopt_net0/components/technologies/ccs/__init__.py
adopt_net0/components/technologies/ccs/ccs.py
adopt_net0/components/technologies/genericTechnologies/__init__.py
adopt_net0/components/technologies/genericTechnologies/conv1.py
adopt_net0/components/technologies/genericTechnologies/conv2.py
adopt_net0/components/technologies/genericTechnologies/conv3.py
adopt_net0/components/technologies/genericTechnologies/conv4.py
adopt_net0/components/technologies/genericTechnologies/fitting_classes.py
adopt_net0/components/technologies/genericTechnologies/res.py
adopt_net0/components/technologies/genericTechnologies/sink.py
adopt_net0/components/technologies/genericTechnologies/stor.py
adopt_net0/components/technologies/specificTechnologies/__init__.py
adopt_net0/components/technologies/specificTechnologies/combined_cycle.py
adopt_net0/components/technologies/specificTechnologies/dac_adsorption.py
adopt_net0/components/technologies/specificTechnologies/gas_turbine.py
adopt_net0/components/technologies/specificTechnologies/heat_pump.py
adopt_net0/components/technologies/specificTechnologies/hydro_open.py
adopt_net0/components/technologies/technology.py
adopt_net0/components/technologies/utilities.py
adopt_net0/components/utilities.py
adopt_net0/data_management/__init__.py
adopt_net0-0.1.10.dist-info/LICENSE
adopt_net0-0.1.10.dist-info/METADATA
adopt_net0-0.1.10.dist-info/WHEEL
adopt_net0-0.1.10.dist-info/RECORD
