Metadata-Version: 2.3
Name: adopt_net0
Version: 0.1.10
Summary: A python package for multi energy system modelling
License: MIT
Author: Jan F. Wiegner
Author-email: j.f.wiegner@uu.nl
Requires-Python: >=3.12,<4.0
Classifier: License :: OSI Approved :: MIT License
Classifier: Programming Language :: Python :: 3
Classifier: Programming Language :: Python :: 3.12
Classifier: Programming Language :: Python :: 3.13
Requires-Dist: Pyomo (>=6.7.1)
Requires-Dist: numpy (>=1.26.4)
Requires-Dist: openpyxl (>=3.1.2)
Requires-Dist: pandas (>=2.2.2)
Requires-Dist: pvlib (>=0.10.4)
Requires-Dist: pwlf (>=2.2.1)
Requires-Dist: requests (>=2.31.0)
Requires-Dist: scandir (>=1.10.0)
Requires-Dist: scipy (>=1.13.0)
Requires-Dist: statsmodels (>=0.14.1)
Requires-Dist: timezonefinder (>=6.5.0)
Requires-Dist: tsam (>=2.3.1)
Project-URL: Documentation, https://adopt-net0.readthedocs.io
Project-URL: Homepage, https://github.com/UU-ER/AdOpT-NET0
Project-URL: Repository, https://github.com/UU-ER/AdOpT-NET0
Project-URL: documentation, https://adopt-net0.readthedocs.io
Project-URL: homepage, https://github.com/UU-ER/AdOpT-NET0
Project-URL: issues, https://github.com/UU-ER/AdOpT-NET0/issues
